tic_watch/__init__.py
tic_watch/telemetry.py
tic_watch-0.1.4.dist-info/METADATA
tic_watch-0.1.4.dist-info/WHEEL
tic_watch-0.1.4.dist-info/top_level.txt
tic_watch-0.1.4.dist-info/RECORD
