Metadata-Version: 2.4
Name: tic_watch
Version: 0.1.4
Summary: TIC Watch package
Home-page: 
Author: TIC
Author-email: Andrews.Rajkumar@dexian.com
Classifier: Programming Language :: Python :: 3
Classifier: Framework :: FastAPI
Classifier: Operating System :: OS Independent
Requires-Python: >=3.7
Requires-Dist: fastapi
Requires-Dist: opentelemetry-api
Requires-Dist: opentelemetry-sdk
Requires-Dist: opentelemetry-instrumentation-fastapi
Requires-Dist: opentelemetry-instrumentation-asgi
Requires-Dist: azure-monitor-opentelemetry-exporterpyjwt>=2.6.0
Requires-Dist: starlette>=0.27.0
Dynamic: author
Dynamic: author-email
Dynamic: classifier
Dynamic: description-content-type
Dynamic: requires-dist
Dynamic: requires-python
Dynamic: summary
